reaper_mcp/__init__.py
reaper_mcp/__main__.py
reaper_mcp/fx.py
reaper_mcp/instructions.py
reaper_mcp/markers.py
reaper_mcp/mcp_core.py
reaper_mcp/midi.py
reaper_mcp/playback.py
reaper_mcp/project.py
reaper_mcp/samples.py
reaper_mcp/tempo.py
reaper_mcp/tracks.py
reaper_mcp/util.py
reaper_mcp-1.2.0.dist-info/METADATA
reaper_mcp-1.2.0.dist-info/WHEEL
reaper_mcp-1.2.0.dist-info/entry_points.txt
reaper_mcp-1.2.0.dist-info/licenses/LICENSE
reaper_mcp-1.2.0.dist-info/RECORD
