Metadata-Version: 2.4
Name: reaper-mcp
Version: 1.2.0
Summary: MCP server for REAPER DAW: project, tracks, MIDI, FX, samples.
Project-URL: Homepage, https://github.com/nbdy/reaper-mcp
Project-URL: Repository, https://github.com/nbdy/reaper-mcp
Project-URL: Issues, https://github.com/nbdy/reaper-mcp/-/issues
Author-email: nbdy <me@nbdy.io>
License-Expression: MIT
License-File: LICENSE
Keywords: audio,daw,mcp,midi,model-context-protocol,music-production,reaper,reapy,vst
Classifier: Development Status :: 4 - Beta
Classifier: Intended Audience :: Developers
Classifier: License :: OSI Approved :: MIT License
Classifier: Programming Language :: Python :: 3
Classifier: Programming Language :: Python :: 3.11
Classifier: Programming Language :: Python :: 3.12
Classifier: Topic :: Multimedia :: Sound/Audio
Classifier: Topic :: Software Development :: Libraries :: Python Modules
Requires-Python: >=3.11
Requires-Dist: fastmcp>=2.12.5
Requires-Dist: pretty-midi>=0.2.10
Requires-Dist: python-reapy>=0.10.0
